setup.py
pyforex/__init__.py
pyforex.egg-info/PKG-INFO
pyforex.egg-info/SOURCES.txt
pyforex.egg-info/dependency_links.txt
pyforex.egg-info/not-zip-safe
pyforex.egg-info/top_level.txt