Metadata-Version: 1.0
Name: pyforex
Version: 0.0.1
Summary: Python Currency Converter and Forex Engine
Home-page: https://github.com/rayattack/pyforex
Author: Raikishi
Author-email: r.ortserga@soothdata.com
License: MIT
Platform: UNKNOWN
